servo_webhooks.py
servo_webhooks-0.2.3.dist-info/entry_points.txt
servo_webhooks-0.2.3.dist-info/LICENSE
servo_webhooks-0.2.3.dist-info/WHEEL
servo_webhooks-0.2.3.dist-info/METADATA
servo_webhooks-0.2.3.dist-info/RECORD
