Metadata-Version: 2.1
Name: servo-webhooks
Version: 0.2.3
Summary: A flexible webhooks connector for Opsani Servo assemblies
Home-page: https://github.com/opsani/servo-webhooks
License: Apache-2.0
Author: Blake Watters
Author-email: blake@opsani.com
Requires-Python: >=3.8,<4.0
Classifier: License :: OSI Approved :: Apache Software License
Classifier: Programming Language :: Python :: 3
Classifier: Programming Language :: Python :: 3.8
Requires-Dist: servox (>=0.7.0)
Project-URL: Repository, https://github.com/opsani/servo-webhooks
